QSCOUT_gatemodels_dev-1.1.0b1.data/data/share/qscout-gatemodels/tests/__init__.py
QSCOUT_gatemodels_dev-1.1.0b1.data/data/share/qscout-gatemodels/tests/parser/__init__.py
QSCOUT_gatemodels_dev-1.1.0b1.data/data/share/qscout-gatemodels/tests/parser/test_jaqalpup_parser.py
qscout/v1/std/jaqal_gates.py
qscout/v1/std/noisy.py
qscout/v1/std/stretched/jaqal_gates.py
QSCOUT_gatemodels_dev-1.1.0b1.dist-info/LICENSE
QSCOUT_gatemodels_dev-1.1.0b1.dist-info/METADATA
QSCOUT_gatemodels_dev-1.1.0b1.dist-info/NOTICE
QSCOUT_gatemodels_dev-1.1.0b1.dist-info/WHEEL
QSCOUT_gatemodels_dev-1.1.0b1.dist-info/top_level.txt
QSCOUT_gatemodels_dev-1.1.0b1.dist-info/RECORD
